beets_ydl-0.0.4.dist-info/METADATA
beets_ydl-0.0.4.dist-info/RECORD
beets_ydl-0.0.4.dist-info/WHEEL
beets_ydl-0.0.4.dist-info/top_level.txt
beetsplug/__init__.py
beetsplug/ydl.py
