Metadata-Version: 2.1
Name: beets-ydl
Version: 0.0.4
Summary: Download audio from youtube-dl soures and import into beets
Home-page: https://github.com/vmassuchetto/beets-ydl
Author: Vinicius Massuchetto
License: UNKNOWN
Platform: UNKNOWN
Classifier: Programming Language :: Python :: 3.6
Classifier: License :: OSI Approved :: MIT License
Classifier: Operating System :: OS Independent
Requires-Dist: beets
Requires-Dist: youtube-dl
Requires-Dist: pyxdg
